pyroml/__init__.py
pyroml/callbacks/__init__.py
pyroml/callbacks/callback.py
pyroml/callbacks/checkpoint.py
pyroml/callbacks/cuda.py
pyroml/callbacks/loggers/__init__.py
pyroml/callbacks/loggers/base_logger.py
pyroml/callbacks/loggers/tensorboard_logger.py
pyroml/callbacks/loggers/wandb_logger.py
pyroml/callbacks/progress/__init__.py
pyroml/callbacks/progress/base_progress.py
pyroml/callbacks/progress/rich_progress.py
pyroml/callbacks/progress/tqdm_progress.py
pyroml/core/__init__.py
pyroml/core/autocast.py
pyroml/core/hparams.py
pyroml/core/model.py
pyroml/core/stage.py
pyroml/core/status.py
pyroml/core/tracker.py
pyroml/core/trainer.py
pyroml/loop/__init__.py
pyroml/loop/base.py
pyroml/loop/eval.py
pyroml/loop/predict.py
pyroml/loop/train.py
pyroml/metrics/__init__.py
pyroml/metrics/accuracy.py
pyroml/models/__init__.py
pyroml/models/backbone.py
pyroml/models/falcon/README.md
pyroml/models/falcon/__init__.py
pyroml/models/falcon/dataset.py
pyroml/models/falcon/graph.py
pyroml/models/falcon/heads.py
pyroml/models/falcon/loss.py
pyroml/models/falcon/metrics.py
pyroml/models/falcon/model.py
pyroml/models/falcon/neighbors.py
pyroml/models/falcon/utils.py
pyroml/models/meta/adaboost/model.py
pyroml/models/utils.py
pyroml/template/base/__init__.py
pyroml/template/base/dataset.py
pyroml/template/cifar100/__init__.py
pyroml/template/cifar100/dataset.py
pyroml/template/flowers102/dataset.py
pyroml/template/imagenet/dataset.py
pyroml/template/iris/__init__.py
pyroml/template/iris/dataset.py
pyroml/template/iris/model.py
pyroml/template/mvtec/dataset.py
pyroml/utils/__init__.py
pyroml/utils/classes.py
pyroml/utils/device.py
pyroml/utils/env.py
pyroml/utils/log.py
pyroml/utils/model.py
pyroml/utils/seed.py
pyroml-2.1.2.dist-info/LICENSE
pyroml-2.1.2.dist-info/METADATA
pyroml-2.1.2.dist-info/WHEEL
pyroml-2.1.2.dist-info/RECORD
