Metadata-Version: 2.3
Name: pyroml
Version: 2.1.2
Summary: Machine Learning framework allowing plug-and-play training for pytorch models
License: MIT License
Author: Nathan MAIRE
Requires-Python: >=3.10
Classifier: License :: Other/Proprietary License
Classifier: Programming Language :: Python :: 3
Classifier: Programming Language :: Python :: 3.10
Classifier: Programming Language :: Python :: 3.11
Classifier: Programming Language :: Python :: 3.12
Classifier: Programming Language :: Python :: 3.13
Provides-Extra: cpu
Provides-Extra: cu124
Provides-Extra: dev
Provides-Extra: extra
Provides-Extra: test
Requires-Dist: datasets (>=3.2.0,<4.0.0)
Requires-Dist: einops ; extra == "extra"
Requires-Dist: gurobipy ; extra == "extra"
Requires-Dist: ipykernel ; extra == "dev"
Requires-Dist: ipywidgets ; extra == "dev"
Requires-Dist: matplotlib (>=3.10.0,<4.0.0)
Requires-Dist: pytest ; extra == "test"
Requires-Dist: rich (>=13.9.4,<14.0.0)
Requires-Dist: safetensors (>=0.5.2,<0.6.0)
Requires-Dist: scikit-learn ; extra == "extra"
Requires-Dist: scipy ; extra == "extra"
Requires-Dist: timm ; extra == "extra"
Requires-Dist: torch (>=2.6.0) ; extra == "cpu"
Requires-Dist: torch (>=2.6.0) ; extra == "cu124"
Requires-Dist: torch-ema ; extra == "extra"
Requires-Dist: torchmetrics (>=1.6.1,<2.0.0)
Requires-Dist: torchvision (>=0.21.0) ; extra == "cpu"
Requires-Dist: torchvision (>=0.21.0) ; extra == "cu124"
Requires-Dist: wandb ; extra == "extra"
Project-URL: github, https://github.com/peacefulotter/pyroml
